qrporter/__init__.py
qrporter/backend.py
qrporter/event_bus.py
qrporter/gui.py
qrporter/qr_generator.py
qrporter/session_manager.py
qrporter/utils.py
qrporter/static/style.css
qrporter/static/assets/icon.ico
qrporter/static/assets/icon.png
qrporter/templates/receive_file.html
qrporter/templates/send_file.html
qrporter-3.0.0.dist-info/licenses/LICENSE
qrporter-3.0.0.dist-info/METADATA
qrporter-3.0.0.dist-info/WHEEL
qrporter-3.0.0.dist-info/entry_points.txt
qrporter-3.0.0.dist-info/top_level.txt
qrporter-3.0.0.dist-info/RECORD
