Metadata-Version: 2.4
Name: qrporter
Version: 3.0.0
Summary: Local Wi‑Fi QR file transfer
Author-email: Manikandan D <manikandan@due.im>
License: MIT License
Project-URL: Homepage, https://due.im/qrporter/
Project-URL: Repository, https://github.com/manikandancode/qrporter
Project-URL: BugTracker, https://github.com/manikandancode/qrporter/issues
Keywords: qr,qr-code,file-transfer,wifi,lan,local-network
Classifier: Development Status :: 5 - Production/Stable
Classifier: Intended Audience :: End Users/Desktop
Classifier: License :: OSI Approved :: MIT License
Classifier: Programming Language :: Python :: 3
Classifier: Programming Language :: Python :: 3.12
Classifier: Programming Language :: Python :: 3.13
Classifier: Framework :: Flask
Classifier: Operating System :: OS Independent
Classifier: Topic :: Internet :: WWW/HTTP
Classifier: Topic :: Communications :: File Sharing
Classifier: Topic :: Software Development :: User Interfaces
Requires-Python: >=3.12
License-File: LICENSE
Requires-Dist: Flask>=3.1.2
Requires-Dist: PySide6>=6.6.1
Requires-Dist: qrcode>=8.2
Requires-Dist: Werkzeug>=3.1.3
Requires-Dist: platformdirs>=4.0.0
Requires-Dist: Pillow>=11.0.0
Dynamic: license-file
